{
    "version": "8.0.12+308",
    "description": "A cross-platform manga app made for e-hentai & exhentai by Flutter",
    "homepage": "https://github.com/HibernalGlow/JHenTai",
    "license": "Apache-2.0",
    "url": "https://github.com/HibernalGlow/JHenTai/releases/download/v8.0.12+308/JHenTai_8.0.12+308_Windows.zip",
    "hash": "f627cf03633636aa08a202dbdbe861d1ef4ec895eefd4c3ce49bf4f1e2e6d89f",
    "extract_dir": "JHenTai_8.0.12+308",
    "bin": "jhentai.exe",
    "shortcuts": [
        [
            "jhentai.exe",
            "JHenTaiX"
        ]
    ],
    "checkver": {
        "url": "https://api.github.com/repos/HibernalGlow/JHenTai/releases/latest",
        "jsonpath": "$.tag_name",
        "regex": "v([\\d.+]+)"
    },
    "autoupdate": {
        "url": "https://github.com/HibernalGlow/JHenTai/releases/download/v$version/JHenTai_$version_Windows.zip",
        "extract_dir": "JHenTai_$version"
    }
}
